{
  "90afab37d054672055a376e5584eefc18841d757d3a073d4ca50c4f3f6799ff8f764bf43f434761f9bb44e53c9a3a78aa657e98e9a5907a3f080eaebdba9ff89": {
    "args": [],
    "kwargs": {
      "code": "css_rsc(d=99)",
      "noise": "depolarize(p=0.01)",
      "repeat": "0"
    },
    "result": {
      "results": {
        "mwpf(c=0)": {
          "errors": 0,
          "discards": 0,
          "elapsed": 1882.2649699488977
        },
        "mwpf(c=50)": {
          "errors": 0,
          "discards": 0,
          "elapsed": 2344.6964047757565
        },
        "mwpf(c=200)": {
          "errors": 0,
          "discards": 0,
          "elapsed": 2512.880725918358
        },
        "fb(max_tree_size=0)": {
          "errors": 0,
          "discards": 0,
          "elapsed": 427.41004957716444
        },
        "fb": {
          "errors": 0,
          "discards": 0,
          "elapsed": 408.64973418721206
        }
      }
    },
    "shots": 1000000,
    "duration": 8869.29956175,
    "min_time": 8869.29956175,
    "finished_tasks": 1
  },
  "9a60aad408d1182defe42fc777b0750711cfcb1558bfc1a4a1f0411494529c416a4dbafb326000e194ce48920ec0d45f9c986ce6a15b8ff3502bc5a4e4639c9c": {
    "args": [],
    "kwargs": {
      "code": "css_rsc(d=99)",
      "noise": "depolarize(p=0.01)",
      "repeat": "1"
    },
    "result": {
      "results": {
        "mwpf(c=0)": {
          "errors": 0,
          "discards": 0,
          "elapsed": 1897.4610688944258
        },
        "mwpf(c=50)": {
          "errors": 0,
          "discards": 0,
          "elapsed": 2352.473490069313
        },
        "mwpf(c=200)": {
          "errors": 0,
          "discards": 0,
          "elapsed": 2537.906534343967
        },
        "fb(max_tree_size=0)": {
          "errors": 0,
          "discards": 0,
          "elapsed": 423.3890171224151
        },
        "fb": {
          "errors": 0,
          "discards": 0,
          "elapsed": 410.9631096052159
        }
      }
    },
    "shots": 1000000,
    "duration": 8917.684852792001,
    "min_time": 8917.684852792001,
    "finished_tasks": 1
  },
  "d56c1e17a5fd1b0ddaf1eed53bce81a97832fe0b8340bc5b52a29110f6ca34b6229d8709c753e7a962146dcaf5a94ee365eefa4f45b064371d697729e9a92dfc": {
    "args": [],
    "kwargs": {
      "code": "css_rsc(d=99)",
      "noise": "depolarize(p=0.01)",
      "repeat": "2"
    },
    "result": {
      "results": {
        "mwpf(c=0)": {
          "errors": 0,
          "discards": 0,
          "elapsed": 1907.69015944444
        },
        "mwpf(c=50)": {
          "errors": 0,
          "discards": 0,
          "elapsed": 2355.164668476594
        },
        "mwpf(c=200)": {
          "errors": 0,
          "discards": 0,
          "elapsed": 2507.6975212438306
        },
        "fb(max_tree_size=0)": {
          "errors": 0,
          "discards": 0,
          "elapsed": 429.2491586656946
        },
        "fb": {
          "errors": 0,
          "discards": 0,
          "elapsed": 414.0193804156731
        }
      }
    },
    "shots": 1000000,
    "duration": 8906.877864,
    "min_time": 8906.877864,
    "finished_tasks": 1
  },
  "d13828ebbc31d88f689dc967ec392e818d52ad370e636d88113c8dd2ae8af1d5f23c3acb3f4b54258c14b54aff6872c58af0c11afe6d8a34f01804becebf4ed0": {
    "args": [],
    "kwargs": {
      "code": "css_rsc(d=99)",
      "noise": "depolarize(p=0.01)",
      "repeat": "3"
    },
    "result": {
      "results": {
        "mwpf(c=0)": {
          "errors": 0,
          "discards": 0,
          "elapsed": 1904.6800012254307
        },
        "mwpf(c=50)": {
          "errors": 0,
          "discards": 0,
          "elapsed": 2357.7665041291975
        },
        "mwpf(c=200)": {
          "errors": 0,
          "discards": 0,
          "elapsed": 2474.416355407348
        },
        "fb(max_tree_size=0)": {
          "errors": 0,
          "discards": 0,
          "elapsed": 429.48094936042486
        },
        "fb": {
          "errors": 0,
          "discards": 0,
          "elapsed": 411.30700171559494
        }
      }
    },
    "shots": 1000000,
    "duration": 8868.984528416,
    "min_time": 8868.984528416,
    "finished_tasks": 1
  },
  "7b307a8eaea11caaf6694f1fc1748bf04a8b28ab6bf15a3f36aebf7fe4c9d450663f0bf64d1212ae55f2896b7dbd95529ff371d313f08999537fcfd93703707f": {
    "args": [],
    "kwargs": {
      "code": "css_rsc(d=99)",
      "noise": "depolarize(p=0.01)",
      "repeat": "4"
    },
    "result": {
      "results": {
        "mwpf(c=0)": {
          "errors": 0,
          "discards": 0,
          "elapsed": 1896.619191639306
        },
        "mwpf(c=50)": {
          "errors": 0,
          "discards": 0,
          "elapsed": 2349.461333586943
        },
        "mwpf(c=200)": {
          "errors": 0,
          "discards": 0,
          "elapsed": 2500.8930006393693
        },
        "fb(max_tree_size=0)": {
          "errors": 0,
          "discards": 0,
          "elapsed": 427.57928174566047
        },
        "fb": {
          "errors": 0,
          "discards": 0,
          "elapsed": 410.7958102208842
        }
      }
    },
    "shots": 1000000,
    "duration": 8896.034233291,
    "min_time": 8896.034233291,
    "finished_tasks": 1
  },
  "8ec683f160ef1ce2710ff8a938cbbee06742e7f3cf9492e0c0ac9a9ff73cd3b113bb577adaef87ed2d659b8346c94a5fed0d3717795a9cfca00260871fa8420b": {
    "args": [],
    "kwargs": {
      "code": "css_rsc(d=81)",
      "noise": "depolarize(p=0.01)",
      "repeat": "0"
    },
    "result": {
      "results": {
        "mwpf(c=0)": {
          "errors": 0,
          "discards": 0,
          "elapsed": 1271.3866511164958
        },
        "mwpf(c=50)": {
          "errors": 0,
          "discards": 0,
          "elapsed": 1823.2347895516941
        },
        "mwpf(c=200)": {
          "errors": 0,
          "discards": 0,
          "elapsed": 1745.2199960576097
        },
        "fb(max_tree_size=0)": {
          "errors": 0,
          "discards": 0,
          "elapsed": 175.84844589413825
        },
        "fb": {
          "errors": 0,
          "discards": 0,
          "elapsed": 181.1695790360954
        }
      }
    },
    "shots": 1000000,
    "duration": 5849.539249875,
    "min_time": 5849.539249875,
    "finished_tasks": 1
  },
  "66d5b0a8423649e67cb80ed29dd9fb92f5103388423d4dfa3e9a429485ebd0f06505858694b7897febbdf5071ce372239008f40acc85d7a2c3046bcf1dc175d7": {
    "args": [],
    "kwargs": {
      "code": "css_rsc(d=81)",
      "noise": "depolarize(p=0.01)",
      "repeat": "1"
    },
    "result": null,
    "shots": 0,
    "duration": 0,
    "min_time": null,
    "finished_tasks": 0
  },
  "f6cf309f226acee759391443ae0512c010c3294fb745cd9cc1a68f465fc3db22994451aafbee426665a7ef3125037453033fbd0fb813a86c8e5b6e94a547f200": {
    "args": [],
    "kwargs": {
      "code": "css_rsc(d=81)",
      "noise": "depolarize(p=0.01)",
      "repeat": "2"
    },
    "result": null,
    "shots": 0,
    "duration": 0,
    "min_time": null,
    "finished_tasks": 0
  },
  "c6410fa3b4efd5c76cffd3baf479a89cb81f489cee8ddd77f9f98c3497febac46ced5e19441c7c8ea8bf3b7f4f20f04672a721a6a6e01f1bf501a4860c4f71f7": {
    "args": [],
    "kwargs": {
      "code": "css_rsc(d=81)",
      "noise": "depolarize(p=0.01)",
      "repeat": "3"
    },
    "result": null,
    "shots": 0,
    "duration": 0,
    "min_time": null,
    "finished_tasks": 0
  },
  "377d34a2f5cf9f6b11221fbfe6c61ef6d1c85771986f6d2c27c3f9019b9c5c822cad3a54537a6c1ff3d8506efc14db324927948179583b7613301832a714e722": {
    "args": [],
    "kwargs": {
      "code": "css_rsc(d=81)",
      "noise": "depolarize(p=0.01)",
      "repeat": "4"
    },
    "result": null,
    "shots": 0,
    "duration": 0,
    "min_time": null,
    "finished_tasks": 0
  },
  "66e9640be3f85d50da5a9ca8220f39ad9140118274ed0242a3e4db812d91149ce4710af1346937e4d1fc982368c698be96405773b550cc08d78bc8ff11d24824": {
    "args": [],
    "kwargs": {
      "code": "css_rsc(d=65)",
      "noise": "depolarize(p=0.01)",
      "repeat": "0"
    },
    "result": null,
    "shots": 0,
    "duration": 0,
    "min_time": null,
    "finished_tasks": 0
  },
  "9bcc5058a742579d506014fd2ff6b1c19acf8dca6a8ca7e1da521e7be2d8213cc781dfe4beb2b05d0c6809fd7f54e9eddfc657c792c27178b8da7e3b27b9d98d": {
    "args": [],
    "kwargs": {
      "code": "css_rsc(d=65)",
      "noise": "depolarize(p=0.01)",
      "repeat": "1"
    },
    "result": {
      "results": {
        "mwpf(c=0)": {
          "errors": 0,
          "discards": 0,
          "elapsed": 718.7991710993828
        },
        "mwpf(c=50)": {
          "errors": 0,
          "discards": 0,
          "elapsed": 1150.8626987921605
        },
        "mwpf(c=200)": {
          "errors": 0,
          "discards": 0,
          "elapsed": 1288.5075720745565
        },
        "fb(max_tree_size=0)": {
          "errors": 0,
          "discards": 0,
          "elapsed": 195.06346540145566
        },
        "fb": {
          "errors": 0,
          "discards": 0,
          "elapsed": 185.7215331466894
        }
      }
    },
    "shots": 1000000,
    "duration": 3719.097997957999,
    "min_time": 3719.097997957999,
    "finished_tasks": 1
  },
  "fb2de2a2be9aaecda8f0b884e604b33112636e655815e9498b9aec45d797428ccaf8bf23a6550f862fe5bb5f7ec7346fe2fc8ee92a9a525c57d61bcf37081597": {
    "args": [],
    "kwargs": {
      "code": "css_rsc(d=65)",
      "noise": "depolarize(p=0.01)",
      "repeat": "2"
    },
    "result": null,
    "shots": 0,
    "duration": 0,
    "min_time": null,
    "finished_tasks": 0
  },
  "5080ab6728468a1928773aa89d9713c88acabb7684a3028b8988744cd23284e97018ec2480d985e54927c66c0f873f427e29b90391e1d0436275527e09f2fd96": {
    "args": [],
    "kwargs": {
      "code": "css_rsc(d=65)",
      "noise": "depolarize(p=0.01)",
      "repeat": "3"
    },
    "result": null,
    "shots": 0,
    "duration": 0,
    "min_time": null,
    "finished_tasks": 0
  },
  "ba65442024b87d7b70d4fa9ec05a54b2f7c671cfa904372fc80290f3a0bcb58763d52c187bc44b3b2e77d4036e5b9d6c93f28ed3953c5f71e2e9d186e96cc952": {
    "args": [],
    "kwargs": {
      "code": "css_rsc(d=65)",
      "noise": "depolarize(p=0.01)",
      "repeat": "4"
    },
    "result": null,
    "shots": 0,
    "duration": 0,
    "min_time": null,
    "finished_tasks": 0
  },
  "0e6a6667fd9ceb3004ec1cda8f5348fb3ebdff90032dd8416ccd0d00a0e036fb93c3ca10051849e8e4d02148848b91cb406fa3f1ab38e994bea7e25dc25e4c9c": {
    "args": [],
    "kwargs": {
      "code": "css_rsc(d=53)",
      "noise": "depolarize(p=0.01)",
      "repeat": "0"
    },
    "result": null,
    "shots": 0,
    "duration": 0,
    "min_time": null,
    "finished_tasks": 0
  },
  "7d16f3e5ae0cd203435f33e249abd07e13f174e2a7ceed11260b3c1f48442ab6c0986fa1fc0e369173c5c8117bc94799c2f067d5b643f876edca6575d8003d91": {
    "args": [],
    "kwargs": {
      "code": "css_rsc(d=53)",
      "noise": "depolarize(p=0.01)",
      "repeat": "1"
    },
    "result": null,
    "shots": 0,
    "duration": 0,
    "min_time": null,
    "finished_tasks": 0
  },
  "8b4e22fb73ef0100d7f8902a969351d9a2db4d08e4513b6b933bfddc1bc54d7d58f61a8be7e3af0051a380fe522d5ffae557ff0cffa7f4c7951ce7c6a42c35ea": {
    "args": [],
    "kwargs": {
      "code": "css_rsc(d=53)",
      "noise": "depolarize(p=0.01)",
      "repeat": "2"
    },
    "result": null,
    "shots": 0,
    "duration": 0,
    "min_time": null,
    "finished_tasks": 0
  },
  "47b08e32e231122fa756990a4bf688cd84e49f772f0a260e9c0dcf17cd4125529849d518e8066ee991fa0c2f626d0509bc9030f0767730ad8fb29ad2ae0719ad": {
    "args": [],
    "kwargs": {
      "code": "css_rsc(d=53)",
      "noise": "depolarize(p=0.01)",
      "repeat": "3"
    },
    "result": null,
    "shots": 0,
    "duration": 0,
    "min_time": null,
    "finished_tasks": 0
  },
  "a8d4086e73760be3f406c938235dc6ed5ccce61f4039026e9dee180337071049fb5c572969adb0951e5e0a8b5f329948b5915c29efe0586c0c7abb18a6fee6d4": {
    "args": [],
    "kwargs": {
      "code": "css_rsc(d=53)",
      "noise": "depolarize(p=0.01)",
      "repeat": "4"
    },
    "result": null,
    "shots": 0,
    "duration": 0,
    "min_time": null,
    "finished_tasks": 0
  },
  "0e283774ef9fecb12ce76e4280c79f75e57e412576970992973c2abc4493980817b303391bfa67c263fa5f5efa3b820989f3e823d39eb112add9d415d3f2242d": {
    "args": [],
    "kwargs": {
      "code": "css_rsc(d=43)",
      "noise": "depolarize(p=0.01)",
      "repeat": "0"
    },
    "result": null,
    "shots": 0,
    "duration": 0,
    "min_time": null,
    "finished_tasks": 0
  },
  "7d5c0fafc019b1cf62a845fbfcf62ef2704c7e4989a94b80d0feb72973cca7db0ee640b1f37282c9ce5d62d24451d7bdadfc8e6c9fb95b172d6fae1da2843374": {
    "args": [],
    "kwargs": {
      "code": "css_rsc(d=43)",
      "noise": "depolarize(p=0.01)",
      "repeat": "1"
    },
    "result": null,
    "shots": 0,
    "duration": 0,
    "min_time": null,
    "finished_tasks": 0
  },
  "8081882ce59cda74c831ab94cf2fbf71a2282b7ace9f56b3450642656fa11388272e84f5d26e2af163322644e1212bc42269950df93ef9455283fd802ce0a3b2": {
    "args": [],
    "kwargs": {
      "code": "css_rsc(d=43)",
      "noise": "depolarize(p=0.01)",
      "repeat": "2"
    },
    "result": null,
    "shots": 0,
    "duration": 0,
    "min_time": null,
    "finished_tasks": 0
  },
  "e3513bd8b280e6635d0db7baf7d6c1adf2d8b96b6d26e5aa94e4d06052c5ba34e1004c3a6ab81c76b42618b7693e41d6c487bdc7b0e69e4fe240a42c6e4ffe29": {
    "args": [],
    "kwargs": {
      "code": "css_rsc(d=43)",
      "noise": "depolarize(p=0.01)",
      "repeat": "3"
    },
    "result": null,
    "shots": 0,
    "duration": 0,
    "min_time": null,
    "finished_tasks": 0
  },
  "60c5fa85cd366b33e4bf3a13bfe98af707960833c57d46447f75d524466259d0d6f61a7e1314f78d28a88cd9a03dd1b12929e24e01638c37b66f991d9af41c8e": {
    "args": [],
    "kwargs": {
      "code": "css_rsc(d=43)",
      "noise": "depolarize(p=0.01)",
      "repeat": "4"
    },
    "result": null,
    "shots": 0,
    "duration": 0,
    "min_time": null,
    "finished_tasks": 0
  },
  "e50b3883132bf0094ef49b1c2d0a0eb3165c26b206d4744b0f413da942daa187897cb7213be50202b3999d01ae7cfeb3863014c0c4aaab7d2f40059a6bba6c4f": {
    "args": [],
    "kwargs": {
      "code": "css_rsc(d=35)",
      "noise": "depolarize(p=0.01)",
      "repeat": "0"
    },
    "result": null,
    "shots": 0,
    "duration": 0,
    "min_time": null,
    "finished_tasks": 0
  },
  "de25012380322f25d631a8cacc32fa0ee31daa90ce688b807881b36bd093610cbbdae5782c0805d9e56fe66d9ee42db39db0fba292b54c04bea6651c9ba5c622": {
    "args": [],
    "kwargs": {
      "code": "css_rsc(d=35)",
      "noise": "depolarize(p=0.01)",
      "repeat": "1"
    },
    "result": null,
    "shots": 0,
    "duration": 0,
    "min_time": null,
    "finished_tasks": 0
  },
  "64d40aa94ae888fcf182dc3098b5ab5e119d4193316625c1da4dfeb1139be81e003d90e3e9a667a0aff4f384c04491711193fbaae7abc444e3768f64c0725601": {
    "args": [],
    "kwargs": {
      "code": "css_rsc(d=35)",
      "noise": "depolarize(p=0.01)",
      "repeat": "2"
    },
    "result": null,
    "shots": 0,
    "duration": 0,
    "min_time": null,
    "finished_tasks": 0
  },
  "3f0130285ec7d6026b6263ddf89c9d9352cf81a82e5ff5aadc976eae50ed3386689eda168fd11293f873140a22e82003ba3cc1ef95f142fb284dee9c69f0cb30": {
    "args": [],
    "kwargs": {
      "code": "css_rsc(d=35)",
      "noise": "depolarize(p=0.01)",
      "repeat": "3"
    },
    "result": null,
    "shots": 0,
    "duration": 0,
    "min_time": null,
    "finished_tasks": 0
  },
  "a54c2ba81f1b27995f8d84781db36eae950c28f36717ac679d44acd42eee373d3f610c3bfe00391b2b76d0d9999bdb525b8cf96e7d3eaaf20ded4ab0bce8451e": {
    "args": [],
    "kwargs": {
      "code": "css_rsc(d=35)",
      "noise": "depolarize(p=0.01)",
      "repeat": "4"
    },
    "result": null,
    "shots": 0,
    "duration": 0,
    "min_time": null,
    "finished_tasks": 0
  },
  "69c54255d3a55a87662362f6780a54cb2f333d4cf901ae72325d522b5b5555cc4050608a683e943d8483867e98c7a6d1a54507a689e6e6e0c1ddd1ee423dc9ce": {
    "args": [],
    "kwargs": {
      "code": "css_rsc(d=27)",
      "noise": "depolarize(p=0.01)",
      "repeat": "0"
    },
    "result": null,
    "shots": 0,
    "duration": 0,
    "min_time": null,
    "finished_tasks": 0
  },
  "fa94aad3143bbb136d09324058eadd027eca317a7c4a894416050221f754c3b641ef0faef43c7503cd7d55ae17b196b2bfeeec80153e9b70c0257a2b1bc80780": {
    "args": [],
    "kwargs": {
      "code": "css_rsc(d=27)",
      "noise": "depolarize(p=0.01)",
      "repeat": "1"
    },
    "result": null,
    "shots": 0,
    "duration": 0,
    "min_time": null,
    "finished_tasks": 0
  },
  "8d2341b39adf681a362ebb9755902c341caeb469361020d1d0e09e83c14cad629eca51fbe70a38405f0a31729608e7fd3a5eddcec09f724e5e2c93a507fb2b82": {
    "args": [],
    "kwargs": {
      "code": "css_rsc(d=27)",
      "noise": "depolarize(p=0.01)",
      "repeat": "2"
    },
    "result": null,
    "shots": 0,
    "duration": 0,
    "min_time": null,
    "finished_tasks": 0
  },
  "8ede99d2760cc964a797ced2948b30bfea7034bf963f2b59e55be6e94d9967170bdb7792c69ebf78ec0d9142c32ac9f3cb0d6e0f1b8b23b36a3492d0e16d5a1f": {
    "args": [],
    "kwargs": {
      "code": "css_rsc(d=27)",
      "noise": "depolarize(p=0.01)",
      "repeat": "3"
    },
    "result": null,
    "shots": 0,
    "duration": 0,
    "min_time": null,
    "finished_tasks": 0
  },
  "0ddff85ad6211a37fe297f36c4b796dfcb02e7b63a1a94ac6792fc0d6601c719b1358fb2a4a22b903808bc9eceb1de4a79f0deeb432e75222d86537c2218e890": {
    "args": [],
    "kwargs": {
      "code": "css_rsc(d=27)",
      "noise": "depolarize(p=0.01)",
      "repeat": "4"
    },
    "result": null,
    "shots": 0,
    "duration": 0,
    "min_time": null,
    "finished_tasks": 0
  },
  "9a1b3aa17a48883ff32b1f6a0cee63d47a6e48fed215e50f28d9295bcc156437f3b399d3c9bdbe6b300987472a05468e4ad7565f714309be4731b028298c344d": {
    "args": [],
    "kwargs": {
      "code": "css_rsc(d=23)",
      "noise": "depolarize(p=0.01)",
      "repeat": "0"
    },
    "result": null,
    "shots": 0,
    "duration": 0,
    "min_time": null,
    "finished_tasks": 0
  },
  "9a4d6896d23fcf6c222126698881b421bf025d640ec787fd06e519a69a2b4fc0c5104fd6f69d153d59d9cb223e9275d009c711914d2e9aa8f5446b34bb5478dc": {
    "args": [],
    "kwargs": {
      "code": "css_rsc(d=23)",
      "noise": "depolarize(p=0.01)",
      "repeat": "1"
    },
    "result": null,
    "shots": 0,
    "duration": 0,
    "min_time": null,
    "finished_tasks": 0
  },
  "f38ffdad1601335d9442b8a2b1ea618a24921f4f9bfd41f9bb408bea1a5693abca318b48d23217aec30b2ee56d35782bb88e2398750d94031405a5ad07cafa15": {
    "args": [],
    "kwargs": {
      "code": "css_rsc(d=23)",
      "noise": "depolarize(p=0.01)",
      "repeat": "2"
    },
    "result": null,
    "shots": 0,
    "duration": 0,
    "min_time": null,
    "finished_tasks": 0
  },
  "7c1d0ec30086a8dd956e4acde9b0ed64fd503f7db631e9d36f982351cb7daa399c7d5efa490c5ec291e661ec53d248c95ecb3cdc2452c5d334508e2700bf03fc": {
    "args": [],
    "kwargs": {
      "code": "css_rsc(d=23)",
      "noise": "depolarize(p=0.01)",
      "repeat": "3"
    },
    "result": null,
    "shots": 0,
    "duration": 0,
    "min_time": null,
    "finished_tasks": 0
  },
  "ab9f088737d7f3f370ac037276ef087af005474c2e2f1654b8549273a516a6a590614a82668131148c29627a9fcb57f65404c5aff5055e9c1b8463ce916fc392": {
    "args": [],
    "kwargs": {
      "code": "css_rsc(d=23)",
      "noise": "depolarize(p=0.01)",
      "repeat": "4"
    },
    "result": null,
    "shots": 0,
    "duration": 0,
    "min_time": null,
    "finished_tasks": 0
  },
  "c7feedece73c8c11a7836b8d56f291d06160b9aa239741a7fcbb72bdbee882e4f65237bfe17aaa73a7c14ae9c7db79a59671fd0998173078e0cc63c5b33e9c55": {
    "args": [],
    "kwargs": {
      "code": "css_rsc(d=19)",
      "noise": "depolarize(p=0.01)",
      "repeat": "0"
    },
    "result": null,
    "shots": 0,
    "duration": 0,
    "min_time": null,
    "finished_tasks": 0
  },
  "b22c700eb6610f9083b642eb5de1e673b2a67798a87bfe38b659b48a95a698b9e041ab99e45b98108e9f3e1fc01a95fbb4062a4d4c2e39df54483fe7e7f5f9bd": {
    "args": [],
    "kwargs": {
      "code": "css_rsc(d=19)",
      "noise": "depolarize(p=0.01)",
      "repeat": "1"
    },
    "result": null,
    "shots": 0,
    "duration": 0,
    "min_time": null,
    "finished_tasks": 0
  },
  "d8747e1970f294ceb8191286ed66e052294dea7d1468721910e5626f80e0b7c760d1107e60006f27bfaf3249b169bbe4ad8c1240dbcc6af6f26885df1d0179ff": {
    "args": [],
    "kwargs": {
      "code": "css_rsc(d=19)",
      "noise": "depolarize(p=0.01)",
      "repeat": "2"
    },
    "result": null,
    "shots": 0,
    "duration": 0,
    "min_time": null,
    "finished_tasks": 0
  },
  "e4a38ec110c3aa1055ec4be7d346a6174b629d93d31a21fcd85c35a7238f75719261e86d241f5ba809a7bcecde5cd5d22965d002687babff5eaa2aa47f3e3bb8": {
    "args": [],
    "kwargs": {
      "code": "css_rsc(d=19)",
      "noise": "depolarize(p=0.01)",
      "repeat": "3"
    },
    "result": null,
    "shots": 0,
    "duration": 0,
    "min_time": null,
    "finished_tasks": 0
  },
  "02a3c768d1581129e5089722a941e827f3f26d019000f4a59571c7d73049e081ed28c8fbbf053f7c652bf67c5d4d12b808bede67406fb896734efb16e5740bd7": {
    "args": [],
    "kwargs": {
      "code": "css_rsc(d=19)",
      "noise": "depolarize(p=0.01)",
      "repeat": "4"
    },
    "result": null,
    "shots": 0,
    "duration": 0,
    "min_time": null,
    "finished_tasks": 0
  },
  "099528db010278774d685a28ac0205075d412099140f691081015cd5996505baa1eeb461eaa0b304ef104758d2e98f115d1ba20f17d09f6cb9db8c74ead63dfa": {
    "args": [],
    "kwargs": {
      "code": "css_rsc(d=15)",
      "noise": "depolarize(p=0.01)",
      "repeat": "0"
    },
    "result": null,
    "shots": 0,
    "duration": 0,
    "min_time": null,
    "finished_tasks": 0
  },
  "a3648fe617fe78e4890abf4ee8fa32edf6204875646e2f5ae15d13cdbcad2cdf91fd7b6a0a02bcc0900a3a4c895951e424080188050413b466914d9405f5dd1b": {
    "args": [],
    "kwargs": {
      "code": "css_rsc(d=15)",
      "noise": "depolarize(p=0.01)",
      "repeat": "1"
    },
    "result": null,
    "shots": 0,
    "duration": 0,
    "min_time": null,
    "finished_tasks": 0
  },
  "7caac4b2cb021d23abe6a72e72278e860ff6e3f644453cfc957a01f378291d815b9cd190e3d9fdb6ff59541b9f3fe90e486b612ad6f49e8b672cd82afa6d1c9c": {
    "args": [],
    "kwargs": {
      "code": "css_rsc(d=15)",
      "noise": "depolarize(p=0.01)",
      "repeat": "2"
    },
    "result": null,
    "shots": 0,
    "duration": 0,
    "min_time": null,
    "finished_tasks": 0
  },
  "7e0ebf2e571747d67101c0d5ece6cb2230ce585d0d68828bcb33c2cf7cedf4f5ae3f1eae23861ca39ddebc5c81ba4440577002ab7dd628108633bd1734423672": {
    "args": [],
    "kwargs": {
      "code": "css_rsc(d=15)",
      "noise": "depolarize(p=0.01)",
      "repeat": "3"
    },
    "result": null,
    "shots": 0,
    "duration": 0,
    "min_time": null,
    "finished_tasks": 0
  },
  "f7acdb768829165cb8322bff6a533f4095a2a3870d78e230ff20f970d997eac26107da4380353b9f018813e20b584635a0e93af330f42ead048281990045ec10": {
    "args": [],
    "kwargs": {
      "code": "css_rsc(d=15)",
      "noise": "depolarize(p=0.01)",
      "repeat": "4"
    },
    "result": null,
    "shots": 0,
    "duration": 0,
    "min_time": null,
    "finished_tasks": 0
  },
  "d5a1df4f3af1edccd068e99bdb17688b237b011edfbd7a96999945193063b279c323f68b849137d030fde82b0fe3ddcaa1273fec4ee56358cb107ca85a502bbc": {
    "args": [],
    "kwargs": {
      "code": "css_rsc(d=13)",
      "noise": "depolarize(p=0.01)",
      "repeat": "0"
    },
    "result": null,
    "shots": 0,
    "duration": 0,
    "min_time": null,
    "finished_tasks": 0
  },
  "cc6f8e09dce5ee609434e8d7f4a68098052f9fdc3c1a6e118865eec02d1efcdd9c225b59878cfab190348ac9f37d0125effe6b6b18f62a9c50dd86a770d13ad3": {
    "args": [],
    "kwargs": {
      "code": "css_rsc(d=13)",
      "noise": "depolarize(p=0.01)",
      "repeat": "1"
    },
    "result": null,
    "shots": 0,
    "duration": 0,
    "min_time": null,
    "finished_tasks": 0
  },
  "1363149a012a50b0474fd9d935ced72b8d5ce6ee1c19ec5ca224ace690acb1bd45a94a6e4134f1a4e33e82eb5156cc3b53a07131f42d6908b5798b794d3292eb": {
    "args": [],
    "kwargs": {
      "code": "css_rsc(d=13)",
      "noise": "depolarize(p=0.01)",
      "repeat": "2"
    },
    "result": null,
    "shots": 0,
    "duration": 0,
    "min_time": null,
    "finished_tasks": 0
  },
  "71a007e738ba2f896e813ef0430305ab51d8e37e06b1ab155f389a75ab460607cbd3cff245285836bb1bfc2f8eb5aa64310c71b71a83e85ba7c6f4f50b4becd9": {
    "args": [],
    "kwargs": {
      "code": "css_rsc(d=13)",
      "noise": "depolarize(p=0.01)",
      "repeat": "3"
    },
    "result": null,
    "shots": 0,
    "duration": 0,
    "min_time": null,
    "finished_tasks": 0
  },
  "5b893409fa0f7f701c0e54f30f81dc61eea8bf1fa8cf923550df33fad4d6cbc5d2e2195d5604ba2033afbbe73297eb0e88556331259e07ed27da70076bc33bff": {
    "args": [],
    "kwargs": {
      "code": "css_rsc(d=13)",
      "noise": "depolarize(p=0.01)",
      "repeat": "4"
    },
    "result": null,
    "shots": 0,
    "duration": 0,
    "min_time": null,
    "finished_tasks": 0
  },
  "cace23fffddad239d3e9eba639a9fcc003722775645a6d98335b9bdcb780b0371bfb9873052d322ad7d6575a231818b336e54146aaed98cc3aa8fa954bc86625": {
    "args": [],
    "kwargs": {
      "code": "css_rsc(d=9)",
      "noise": "depolarize(p=0.01)",
      "repeat": "0"
    },
    "result": null,
    "shots": 0,
    "duration": 0,
    "min_time": null,
    "finished_tasks": 0
  },
  "56fa61921b67d04924ae8573891f84e6fd054f084ec5f302d82ca7e54205a960d77d803f3f89d00899cb3f2d41843a6660a0355d64f7d998466b6f06ffb211af": {
    "args": [],
    "kwargs": {
      "code": "css_rsc(d=9)",
      "noise": "depolarize(p=0.01)",
      "repeat": "1"
    },
    "result": null,
    "shots": 0,
    "duration": 0,
    "min_time": null,
    "finished_tasks": 0
  },
  "f6505dc715691f7a22b9e91a59c5f717747faff8c2309128bbde60414f599b41359e74c2c716f27e36227dd0a62735bfbbbfcefc77f4648a773dc8d2a912627e": {
    "args": [],
    "kwargs": {
      "code": "css_rsc(d=9)",
      "noise": "depolarize(p=0.01)",
      "repeat": "2"
    },
    "result": null,
    "shots": 0,
    "duration": 0,
    "min_time": null,
    "finished_tasks": 0
  },
  "61f3cc401f15a774aa4c17b72119cb161a3b814d94c504212c1057afee44e3c7b24d3eabfc35432e192f09c8ae39a3d04879219d48345aeedf2581560b558e81": {
    "args": [],
    "kwargs": {
      "code": "css_rsc(d=9)",
      "noise": "depolarize(p=0.01)",
      "repeat": "3"
    },
    "result": null,
    "shots": 0,
    "duration": 0,
    "min_time": null,
    "finished_tasks": 0
  },
  "865c231b6304c885155d43d2be3fa9720323f37ff3b7b3e3e04d3f7f656daeba248e217c98596425aeba1f68337b70b2d225eb4729a9bf8f27ea706bafeddc3f": {
    "args": [],
    "kwargs": {
      "code": "css_rsc(d=9)",
      "noise": "depolarize(p=0.01)",
      "repeat": "4"
    },
    "result": null,
    "shots": 0,
    "duration": 0,
    "min_time": null,
    "finished_tasks": 0
  },
  "3b4c2f72e1a5e3ef8534235925e01445dc4b9b98644494f3f5e17e8d7e9fe3cdf1947ce2a60b9761cf04a6ebddd156f695c33fe4be38457533c4c736b35dcde0": {
    "args": [],
    "kwargs": {
      "code": "css_rsc(d=7)",
      "noise": "depolarize(p=0.01)",
      "repeat": "0"
    },
    "result": null,
    "shots": 0,
    "duration": 0,
    "min_time": null,
    "finished_tasks": 0
  },
  "2f4079a477f923fa85d4db395ab18d78f4a029aa8f36141f4a5ee39084472c0e0cd3f3fc305db794900a3cbcd1a7ca8d62bcfe60186a1fd32b61207a6a5c1c59": {
    "args": [],
    "kwargs": {
      "code": "css_rsc(d=7)",
      "noise": "depolarize(p=0.01)",
      "repeat": "1"
    },
    "result": null,
    "shots": 0,
    "duration": 0,
    "min_time": null,
    "finished_tasks": 0
  },
  "df1884e82ca269db38d23046ed517611db089da6a2ecbd86243b2ce43791d50f802376d47a348965cb613f4084079b235fd6494d8c097b162d6adc18a1a17275": {
    "args": [],
    "kwargs": {
      "code": "css_rsc(d=7)",
      "noise": "depolarize(p=0.01)",
      "repeat": "2"
    },
    "result": null,
    "shots": 0,
    "duration": 0,
    "min_time": null,
    "finished_tasks": 0
  },
  "fac28082bb552acd4b381a7ff188dc0f66c95958ab0803a47c85543230897b4eb55ab0bcf93a98df19faab8e6d68f0c37522cf52a03182cf000ffca604593d9b": {
    "args": [],
    "kwargs": {
      "code": "css_rsc(d=7)",
      "noise": "depolarize(p=0.01)",
      "repeat": "3"
    },
    "result": null,
    "shots": 0,
    "duration": 0,
    "min_time": null,
    "finished_tasks": 0
  },
  "66a720b7afe1fc02f3f70dc59fd30fba5c25f8c24a202e636dd3544cf2b3a6bee687854b588bb277eaf03dbd94d2d67b39c850d3f25e110401f77a4fd411d4e8": {
    "args": [],
    "kwargs": {
      "code": "css_rsc(d=7)",
      "noise": "depolarize(p=0.01)",
      "repeat": "4"
    },
    "result": null,
    "shots": 0,
    "duration": 0,
    "min_time": null,
    "finished_tasks": 0
  },
  "eac1b798c6c5fc93d7df7eb4a21e4436fcc0e11e2c3f2a71120bebfc0bf1d576564f43e0d6d0e5a33df61c6ac865713fefab3d1e6deaf758ed9f0ae4b1f75123": {
    "args": [],
    "kwargs": {
      "code": "css_rsc(d=5)",
      "noise": "depolarize(p=0.01)",
      "repeat": "0"
    },
    "result": null,
    "shots": 0,
    "duration": 0,
    "min_time": null,
    "finished_tasks": 0
  },
  "41754b0cd3b280b365b788d06c29e97f8666d7667249950a82259c102f413b30732845b9fbb1d7e699dff3830c5ac65d17178d2d6d968d32e935394f730dcde8": {
    "args": [],
    "kwargs": {
      "code": "css_rsc(d=5)",
      "noise": "depolarize(p=0.01)",
      "repeat": "1"
    },
    "result": null,
    "shots": 0,
    "duration": 0,
    "min_time": null,
    "finished_tasks": 0
  },
  "21ace3219eede8b52050eb792e1ed2b4489baa36cab33fe11f19be8bbbbce3275bdc94336ba16cd62a622f00b3074f4d20b815019380fbdb0d3902a2bd29482e": {
    "args": [],
    "kwargs": {
      "code": "css_rsc(d=5)",
      "noise": "depolarize(p=0.01)",
      "repeat": "2"
    },
    "result": null,
    "shots": 0,
    "duration": 0,
    "min_time": null,
    "finished_tasks": 0
  },
  "1cf069980bbefb1c4fb622f23a6915d640ef1baa297ca6d3b2f3b599e6649b9d3403c870ebb1e7f2bb9129c74717e644f7f1ee3799dec769a3498bb56ad87a87": {
    "args": [],
    "kwargs": {
      "code": "css_rsc(d=5)",
      "noise": "depolarize(p=0.01)",
      "repeat": "3"
    },
    "result": null,
    "shots": 0,
    "duration": 0,
    "min_time": null,
    "finished_tasks": 0
  },
  "8e4b80a48a2a9aff6c33bfa726551647e862199add8fbe050268ddeb7ecaffbabf09bab2f5d25093d7e6112bb99ef9fb72e19cbcebc5b0105a2de0b65f824e67": {
    "args": [],
    "kwargs": {
      "code": "css_rsc(d=5)",
      "noise": "depolarize(p=0.01)",
      "repeat": "4"
    },
    "result": null,
    "shots": 0,
    "duration": 0,
    "min_time": null,
    "finished_tasks": 0
  },
  "abb01ff936112ce0632aa9e542f148135244be5ff1cb8a0518024daf063023cc5785b5ca6d23ad9c6e64b90c444ce36947b9694592d9d1ea85be5088b0d696d5": {
    "args": [],
    "kwargs": {
      "code": "css_rsc(d=3)",
      "noise": "depolarize(p=0.01)",
      "repeat": "0"
    },
    "result": null,
    "shots": 0,
    "duration": 0,
    "min_time": null,
    "finished_tasks": 0
  },
  "53a14e720632615c87cc67c8e14e74649c6cebb6ea6f4aedb2a5b72241979e0c33094b8f7c28093fb401f8fe53568a131bc0ac12a5d8a8889d9ab1d995b59318": {
    "args": [],
    "kwargs": {
      "code": "css_rsc(d=3)",
      "noise": "depolarize(p=0.01)",
      "repeat": "1"
    },
    "result": null,
    "shots": 0,
    "duration": 0,
    "min_time": null,
    "finished_tasks": 0
  },
  "067ea42a4c2f7a645017ac8febca3d4dca0441ebabacfc668b371e9aa2724855d5a6c45acdee331508f46a13b4f5c2517d5cb7d273d8bf86d81a29514f3cd3af": {
    "args": [],
    "kwargs": {
      "code": "css_rsc(d=3)",
      "noise": "depolarize(p=0.01)",
      "repeat": "2"
    },
    "result": null,
    "shots": 0,
    "duration": 0,
    "min_time": null,
    "finished_tasks": 0
  },
  "cff71e147501a80a32fca142b6852fc6b70e9bf87de47937bb36cc26e768559610ed130d048e1d87b2ef91979f46ec50961c642801d847c52552479a5fa90963": {
    "args": [],
    "kwargs": {
      "code": "css_rsc(d=3)",
      "noise": "depolarize(p=0.01)",
      "repeat": "3"
    },
    "result": null,
    "shots": 0,
    "duration": 0,
    "min_time": null,
    "finished_tasks": 0
  },
  "cd5995c35f538151f627681a8b80fd46da96e74ff87eb7643481a9e3df66657a6e6124dfd1dc3191e29314fef8d7cda0b37776bcc8cf15be0117447baab2ebff": {
    "args": [],
    "kwargs": {
      "code": "css_rsc(d=3)",
      "noise": "depolarize(p=0.01)",
      "repeat": "4"
    },
    "result": null,
    "shots": 0,
    "duration": 0,
    "min_time": null,
    "finished_tasks": 0
  }
}